{"word": "aristocrat", "accent": "/\u0259\u02c8r\u026ast\u0259kr\u00e6t/", "mean_cn": "n. \u8d35\u65cf", "mean_en": "a member of an aristocracy", "sentence": "She was born an aristocrat who lived a life of luxury.", "sentence_trans": "\u5979\u5929\u751f\u5c31\u662f\u4e00\u4f4d\u8fc7\u7740\u5bcc\u8d35\u751f\u6d3b\u7684\u8d35\u65cf\u3002", "sentence_phrase": "", "word_etyma": "aristo\u914d\u5408 \uff0b crat\u7edf\u6cbb\uff0c\u6743\u5229 \u2192 aristocrat\u8d35\u65cf", "cloze_data": {"syllable": "aris-to-crat", "cloze": "[ar]is-to-crat", "options": ["er|ir|or|ur|a"], "tips": [["[ar]isard", "[ar]istate"]]}}