{"word": "attachment", "accent": "/\u0259\u02c8t\u00e6t\u0283m\u0259nt/", "mean_cn": "n. \uff08\u673a\u5668\u7684\u3001\u901a\u8fc7\u90ae\u4ef6\u53d1\u9001\u7684\uff09\u9644\u4ef6", "mean_en": "strong feelings of affection or loyalty for someone or something", "sentence": "I have sent my resume by attachment.", "sentence_trans": "\u6211\u4ee5\u9644\u4ef6\u7684\u5f62\u5f0f\u53d1\u9001\u4e86\u7b80\u5386\u3002", "sentence_phrase": "by attachment", "word_etyma": "attach\u9644\u52a0 + ment\u8868\u540d\u8bcd \u2192 \u9644\u5c5e\u7269", "cloze_data": {"syllable": "at-tach-ment", "cloze": "attach-m[en]t", "options": ["in|on|un|an|e|i|a|o|u"], "tips": [["cem[en]t", "dem[en]t"]]}}