{"word": "automate", "accent": "/\u02c8\u0254\u02d0t\u0259me\u026at/", "mean_cn": "v. \u4f7f\u81ea\u52a8\u5316\uff0c\u81ea\u52a8\u64cd\u4f5c", "mean_en": "to use machines and computers instead of people to do a job or task", "sentence": "We have machines to automate the painting.", "sentence_trans": "\u6211\u4eec\u6709\u673a\u5668\u81ea\u52a8\u55b7\u6f06\u3002", "sentence_phrase": "", "word_etyma": "auto\u81ea\u52a8 \uff0b mate\u4f7f\u4e4b\u6210... \u2192 automate\u4f7f\u81ea\u52a8\u5316\uff0c\u81ea\u52a8\u64cd\u4f5c", "cloze_data": {}}