{"word": "be confident in", "accent": "/bi\u02c8k\u0251nf\u0259d\u0259nt \u026an/", "mean_cn": "phr. \u5bf9\u2026\u6709\u4fe1\u5fc3\uff1b\u5bf9\u2026\u2026\u5145\u6ee1\u4fe1\u5fc3", "mean_en": "full of conviction", "sentence": "Her smile shows that she is really confident in her upcoming interview.", "sentence_trans": "\u5979\u7684\u5fae\u7b11\u8868\u660e\u5979\u5bf9\u5373\u5c06\u5230\u6765\u7684\u9762\u8bd5\u5145\u6ee1\u81ea\u4fe1\u3002", "sentence_phrase": "", "word_etyma": "", "cloze_data": {}}