{"word": "bond", "accent": "/b\u0251\u02d0nd/", "mean_cn": "n. \u8054\u7cfb\uff1b\u675f\u7f1a\u7269\uff0c\u8054\u7ed3\u7269\uff1b  vi. \u56e2\u7ed3\u4e00\u81f4", "mean_en": "a uniting or binding element or force", "sentence": "Everyone has a bond with another person in this web.", "sentence_trans": "\u5728\u8fd9\u5f20\u7f51\u7edc\u4e2d\uff0c\u6bcf\u4e2a\u4eba\u90fd\u4e0e\u5176\u4ed6\u4eba\u6709\u5173\u7cfb\u3002", "sentence_phrase": "a bond with another person", "word_etyma": "", "cloze_data": {"syllable": "bond", "cloze": "b[on]d", "options": ["en|in|un|an|e|i|a|o|u"], "tips": [["b[on]ded", "inb[on]d"]]}}