{"word": "cheer", "accent": "/t\u0283\u026ar/", "mean_cn": "v. \u6b22\u547c\uff1b\u9f13\u52b2\uff0c\u4f7f\u632f\u4f5c\uff1b  n. \u9f13\u52b1\uff0c\u632f\u594b", "mean_en": "to shout loudly, to show support or praise for somebody, or to give them encouragement", "sentence": "The sports fans cheered for their team.", "sentence_trans": "\u7403\u8ff7\u4eec\u4e3a\u4ed6\u4eec\u7684\u7403\u961f\u52a0\u6cb9\u559d\u5f69\u3002", "sentence_phrase": "", "word_etyma": "", "cloze_data": {"syllable": "cheer", "cloze": "ch[eer]", "options": ["ear|ier|eir|air"], "tips": [["ch[eer]er", "ch[eer]ly"]]}}