{"word": "chicken", "accent": "/\u02c8t\u0283\u026ak\u026an/", "mean_cn": "n.\u9e21\u8089\uff1b  vi.\u754f\u7f29\u4e0d\u524d\uff1b  adj.\u80c6\u5c0f\u7684", "mean_en": "meat from a chicken", "sentence": "He cooked chicken for dinner.", "sentence_trans": "\u4ed6\u665a\u9910\u505a\u4e86\u9e21\u8089\u3002", "sentence_phrase": "", "word_etyma": "chick\u5c0f\u9e21 + en\u540d\u8bcd\u540e\u7f00 \u2192 chicken\u5c0f\u9e21", "cloze_data": {"syllable": "chick-en", "cloze": "chi[ck]-en", "options": ["que|kn|ng|nk"], "tips": [["chi[ck]", "chi[ck]er"]]}}