{"word": "choir", "accent": "/\u02c8kwa\u026a\u0259r/", "mean_cn": "n. \uff08\u6559\u4f1a\u7684\uff09\u6b4c\u5531\u961f\uff0c\u5531\u8bd7\u73ed", "mean_en": "a group of people who sing together, for example in church services or public performances", "sentence": "A penguin choir sings Christmas songs.", "sentence_trans": "\u4e00\u4e2a\u4f01\u9e45\u5531\u8bd7\u73ed\u5531\u7740\u5723\u8bde\u6b4c\u3002", "sentence_phrase": "A penguin choir", "word_etyma": "", "cloze_data": {"syllable": "choir", "cloze": "cho[ir]", "options": ["ar|er|or|ur|a"], "tips": [["cho[ir]man", "cho[ir]boy"]]}}