{"word": "compel", "accent": "/k\u0259m\u02c8pel/", "mean_cn": "vt.\u5f3a\u8feb\uff1b\u8feb\u4f7f\u5c48\u670d\uff1b\uff08\u4f7f\uff09\u4e0d\u5f97\u5df2", "mean_en": "to force somebody to do something; to make something necessary", "sentence": "He was compelled to stay in the circle.", "sentence_trans": "\u4ed6\u88ab\u8feb\u5f85\u5728\u4e00\u4e2a\u5706\u5708\u91cc\u3002", "sentence_phrase": "", "word_etyma": "com\u5171\u540c + pel\u63a8 \u2192 \u4e00\u8d77\u63a8 \u2192 \u5f3a\u8feb", "cloze_data": {"syllable": "com-pel", "cloze": "com-p[el]", "options": ["al|le|nl|ol"], "tips": [["exp[el]", "imp[el]"]]}}