{"word": "contradictory", "accent": "/\u02cck\u0251\u02d0ntr\u0259\u02c8d\u026akt\u0259ri/", "mean_cn": "adj.\u5bf9\u7acb\u7684\uff0c\u76f8\u4e92\u77db\u76fe\u7684\uff1b  n.\u77db\u76fe\u7684\u4e8b\u7269", "mean_en": "containing or showing a contradiction", "sentence": "The gestures he is making are contradictory to what he is saying.", "sentence_trans": "\u4ed6\u6bd4\u51fa\u7684\u624b\u52bf\u4e0e\u4ed6\u6240\u8bf4\u7684\u8bdd\u662f\u81ea\u76f8\u77db\u76fe\u7684\u3002", "sentence_phrase": "", "word_etyma": "contra\u53cd\u9a73 + dict\u8bf4\u8bdd\uff0c\u65ad\u8a00 + ory\u5f62\u5bb9\u8bcd\u540e\u7f00 \u2192 contradictory\u77db\u76fe\u7684\uff0c\u5bf9\u7acb\u7684", "cloze_data": {"syllable": "con-tra-dic-to-ry", "cloze": "c[on]-tra-d[i]c-to-ry", "options": ["en|in|un|an|e|i|a|o|u", "a|e|o|u"], "tips": [["c[on]", "ic[on]"], ["Ud[i]c", "asd[i]c"]]}}