{"word": "currency", "accent": "/\u02c8k\u025c\u02d0r\u0259nsi/", "mean_cn": "n. \u8d27\u5e01\uff1b\u6d41\u901a", "mean_en": "the fact that something is used or accepted by a lot of people", "sentence": "In different countries, we must use a different currency to buy things.", "sentence_trans": "\u5728\u4e0d\u540c\u7684\u56fd\u5bb6\uff0c\u6211\u4eec\u5f97\u7528\u4e0d\u540c\u7684\u8d27\u5e01\u6765\u4e70\u4e1c\u897f\u3002", "sentence_phrase": "", "word_etyma": "curr\u8dd1\uff0c\u53d1\u751f + ency\u8868\u540d\u8bcd\uff0c\u6027\u8d28\u72b6\u6001 \u2192 \u8dd1\u6765\u8dd1\u53bb\u7684\u94b1 \u2192 \u6d41\u901a\u8d27\u5e01", "cloze_data": {"syllable": "cur-ren-cy", "cloze": "c[ur]ren-cy", "options": ["ar|er|ir|or|a"], "tips": [["dec[ur]rency", "rec[ur]rency"]]}}