{"word": "distinguish", "accent": "/d\u026a\u02c8st\u026a\u014b\u0261w\u026a\u0283/", "mean_cn": "v.\u533a\u522b\uff0c\u8bc6\u522b", "mean_en": "to recognize the difference between two people or things; to be a characteristic that makes two people, animals or things different; to be able to see or hear something", "sentence": "It's easy to distinguish the blue man from the gray men.", "sentence_trans": "\u6211\u4eec\u5f88\u5bb9\u6613\u5c31\u80fd\u628a\u8fd9\u4e2a\u5c0f\u84dd\u4eba\u4ece\u4e00\u7fa4\u5c0f\u7070\u4eba\u4e2d\u8fa8\u522b\u51fa\u6765\u3002", "sentence_phrase": "", "word_etyma": "dis\u5206\u6563\uff0c\u5206\u5f00 + tingu=ting\u505a\u6807\u8bb0 + ish\u52a8\u8bcd\u540e\u7f00 \u2192 \u5206\u5f00\u505a\u6807\u8bb0 \u2192 distinguish\u533a\u522b", "cloze_data": {"syllable": "dis-tin-guish", "cloze": "dis-tin-g[ui]sh", "options": ["aa|ae|ai|ao|au|ea|ee|ei|eo|eu|ia|ie|ii|io|iu|oa|oe|oi|oo|ou|ua|ue|uo|uu|ay|ey|ow|oy|ur|al|ir|or|er|ar|a|e|i|o|u"], "tips": [["e-q[ui]p", "e-q[ui]-va-lent"]]}}