{"word": "eject", "accent": "/i\u02c8d\u0292ekt/", "mean_cn": "v.\uff08\u4f7f\uff09\u5f39\u51fa\uff1b\u55b7\u5c04\uff1b\u653e\u9010", "mean_en": "to push something out suddenly and with a lot of force; when you eject a disk, tape, etc., or when it ejects, it comes out of the machine after you have pressed a button", "sentence": "I eject the DVD from the DVD player.", "sentence_trans": "\u6211\u628aDVD\u4eceDVD\u673a\u91cc\u5f39\u4e86\u51fa\u6765\u3002", "sentence_phrase": "", "word_etyma": "e\u51fa\uff0c\u51fa\u6765 + ject\u63b7 \u2192 eject\u63b7\u51fa", "cloze_data": {"syllable": "e-ject", "cloze": "e-j[e]ct", "options": ["a|i|o|u"], "tips": [["adj[e]ct", "dej[e]ct"]]}}