{"word": "elsewhere", "accent": "/\u02ccels\u02c8wer/", "mean_cn": "adv.\u5411\u522b\u5904\uff0c\u5728\u522b\u5904", "mean_en": "in, at or to another place", "sentence": "I want to move elsewhere because it's too noisy here.", "sentence_trans": "\u6211\u60f3\u642c\u5230\u522b\u5904\u53bb\uff0c\u56e0\u4e3a\u8fd9\u513f\u592a\u5435\u4e86\u3002", "sentence_phrase": "", "word_etyma": "else\u522b\u7684 + where\u5730\u65b9 \u2192 elsewhere\u5728\u522b\u5904", "cloze_data": {"syllable": "else-where", "cloze": "else-wh[ere]", "options": ["are|ire|ore|ure"], "tips": [["wh[ere]as", "wh[ere]at"]]}}