{"word": "engage", "accent": "/\u026an\u02c8\u0261e\u026ad\u0292/", "mean_cn": "v.\u4f7f\u52a0\u5165\uff0c\u4f7f\u878d\u5165\uff1b\uff08\u519b\u961f\uff09\u4ea4\u6218", "mean_en": "to begin fighting with somebody", "sentence": "She used to exercise alone, but now she engages in the group running.", "sentence_trans": "\u5979\u4e4b\u524d\u4e00\u822c\u72ec\u81ea\u953b\u70bc\uff0c\u4f46\u73b0\u5728\u5979\u52a0\u5165\u4e86\u96c6\u4f53\u8dd1\u6b65\u7684\u884c\u5217\u3002", "sentence_phrase": "engages in", "word_etyma": "", "cloze_data": {"syllable": "en-gage", "cloze": "en-g[a]ge", "options": ["e|i|o|u|aa|ae|ai|ao|au|ea|ee|ei|eo|eu|ia|ie|ii|io|iu|oa|oe|oi|oo|ou|ua|ue|ui|uo|uu|ay|ey|ow|oy|ur|al|ir|or|er|ar"], "tips": [["em-br[a]ce", "lo-c[a]te"]]}}