{"word": "fame", "accent": "/fe\u026am/", "mean_cn": "n.\u540d\u671b\uff0c\u540d\u58f0\uff0c\u58f0\u8a89\uff1b  vt.\u4f7f\u6709\u540d\uff0c\u4f7f\u8457\u540d", "mean_en": "the condition of being known or recognized by many people", "sentence": "The actor enjoys fame and loves the attention it brings him.", "sentence_trans": "\u8fd9\u4f4d\u7537\u6f14\u5458\u6c89\u6d78\u5728\u540d\u671b\u4e2d\uff0c\u5e76\u4eab\u53d7\u7740\u7531\u6b64\u5e26\u6765\u7684\u5173\u6ce8\u5ea6\u3002", "sentence_phrase": "", "word_etyma": "", "cloze_data": {"syllable": "fame", "cloze": "f[a]me", "options": ["e|i|o|u"], "tips": [["bef[a]me", "def[a]me"]]}}