{"word": "fear", "accent": "/f\u026ar/", "mean_cn": "v.\u5bb3\u6015\uff1b\u656c\u754f\uff1b  n.\u6050\u60e7", "mean_en": "to be frightened of somebody/something or frightened of doing something", "sentence": "The girl feared the dog because it might bite her.", "sentence_trans": "\u8fd9\u4e2a\u5973\u5b69\u5bb3\u6015\u8fd9\u53ea\u72d7\uff0c\u56e0\u4e3a\u5b83\u53ef\u80fd\u4f1a\u54ac\u5979\u3002", "sentence_phrase": "", "word_etyma": "", "cloze_data": {"syllable": "fear", "cloze": "f[ear]", "options": ["eer|ier|eir|air"], "tips": [["f[ear]ful", "f[ear]er"]]}}