{"word": "flexible", "accent": "/\u02c8fleks\u0259bl/", "mean_cn": "adj.\u6613\u5f2f\u66f2\u7684\uff0c\u67d4\u8f6f\u7684", "mean_en": "able to change to suit new conditions or situations; able to bend easily without breaking", "sentence": "The pencil is flexible enough to be knotted.", "sentence_trans": "\u8fd9\u652f\u94c5\u7b14\u975e\u5e38\u67d4\u8f6f\uff0c\u751a\u81f3\u53ef\u4ee5\u6253\u7ed3\u3002", "sentence_phrase": "", "word_etyma": "flex\u5f2f\u66f2 + ible\u80fd\u2026\u2026\u7684 \u2192 \u6613\u66f2\u7684", "cloze_data": {"syllable": "fle-xi-ble", "cloze": "fle-xi-[ble]", "options": ["tle|ple|dle|gle"], "tips": [["re-spon-si-[ble]", "sen-si-[ble]"]]}}