{"word": "game", "accent": "/\u0261e\u026am/", "mean_cn": "n.\u6e38\u620f\uff0c\u6bd4\u8d5b\uff1b  adj.\u7518\u613f\u5c1d\u8bd5\u7684\uff0c\u6709\u5192\u9669\u7cbe\u795e\u7684", "mean_en": "an activity or a sport with rules in which people or teams compete against each other", "sentence": "We had a good time playing the board game together.", "sentence_trans": "\u6211\u4eec\u4e00\u8d77\u73a9\u684c\u6e38\u73a9\u5f97\u5f88\u5f00\u5fc3\u3002", "sentence_phrase": "board game", "word_etyma": "", "cloze_data": {"syllable": "game", "cloze": "g[a]me", "options": ["e|i|o|u"], "tips": [["g[a]mely", "g[a]meful"]]}}