{"word": "gratuity", "accent": "/\u0261r\u0259\u02c8tu\u02d0\u0259ti/", "mean_cn": "n. \u8d4f\u94b1\uff0c\u5c0f\u8d39", "mean_en": "an amount of money given to a person (such as a waiter or waitress) who has performed a service", "sentence": "He gave the paperboy a handsome gratuity.", "sentence_trans": "\u4ed6\u7ed9\u4e86\u9001\u62a5\u7684\u5c0f\u5b69\u4e00\u7b14\u4e30\u539a\u7684\u8d4f\u94b1\u3002", "sentence_phrase": "a handsome gratuity", "word_etyma": "gratu=grat\u611f\u6fc0\uff0c\u9ad8\u5174 \uff0b ity \u2192 \u56e0\u611f\u6fc0\u7ed9 \u2192 \u8d4f\u94b1 \u2192 gratuity\u5c0f\u8d39", "cloze_data": {"syllable": "gra-tu-ity", "cloze": "gra-t[u]-ity", "options": ["a|e|i|o"], "tips": [["t[u]", "ut[u]"]]}}