{"word": "humiliate", "accent": "/hju\u02d0\u02c8m\u026alie\u026at/", "mean_cn": "vt. \u7f9e\u8fb1\uff1b\u4f7f\u8499\u803b", "mean_en": "to make somebody feel ashamed or stupid and lose the respect of other people", "sentence": "The\u00a0poor\u00a0boy\u00a0was\u00a0badly\u00a0humiliated\u00a0at\u00a0school.", "sentence_trans": "\u90a3\u4e2a\u53ef\u601c\u7684\u7537\u5b69\u5728\u5b66\u6821\u906d\u53d7\u4e86\u4e25\u91cd\u7684\u7f9e\u8fb1\u3002", "sentence_phrase": "", "word_etyma": "hum\u571f\uff0c\u5730 \uff0b ili \uff0b ate\u4f7f\u4e4b\u6210\u2026 \u2192 \u4f7f\u4eba\u8d34\u5230\u5730\u4e0a \u2192 humiliate\u7f9e\u8fb1\uff0c\u4fae\u8fb1", "cloze_data": {"syllable": "hu-mi-li-ate", "cloze": "hu-m[i]-l[i]-ate", "options": ["a|e|o|u", "a|e|o|u"], "tips": [["m[i]", "Am[i]"], ["aml[i]", "l[i]"]]}}