{"word": "income", "accent": "/\u02c8\u026ank\u028cm/", "mean_cn": "n.\u6536\u5165\uff0c\u6536\u76ca", "mean_en": "the money that a person, a region, a country, etc. earns from work, from investing money, from business, etc.", "sentence": "The man feels happy when receiving his monthly income.", "sentence_trans": "\u6536\u5230\u5f53\u6708\u5de5\u8d44\u65f6\uff0c\u8fd9\u4e2a\u7537\u4eba\u975e\u5e38\u5f00\u5fc3\u3002", "sentence_phrase": "", "word_etyma": "in \u5411\u5185\uff0c\u8fdb\u5165 + come\u6765 \u2192 \u6536\u5165\uff1b\u6536\u76ca\uff1b\u8fdb\u6b3e", "cloze_data": {"syllable": "in-come", "cloze": "[in]-come", "options": ["en|on|un|an|e|i|a|o|u"], "tips": [["[in]", "[in]by"]]}}