{"word": "indeed", "accent": "/\u026an\u02c8di\u02d0d/", "mean_cn": "adv.\u7684\u786e\uff1b\u5b9e\u9645\u4e0a", "mean_en": "used to emphasize a positive statement or answer; used to add information to a statement", "sentence": "I indeed lost sleep last night.", "sentence_trans": "\u6211\u6628\u665a\u7684\u786e\u5931\u7720\u4e86\u3002", "sentence_phrase": "", "word_etyma": "", "cloze_data": {"syllable": "in-deed", "cloze": "in-d[ee]d", "options": ["ea|ie|ii|ye|e"], "tips": [["d[ee]d", "red[ee]d"]]}}