{"word": "inmate", "accent": "/\u02c8\u026anme\u026at/", "mean_cn": "n.\u56da\u72af\uff1b\uff08\u7cbe\u795e\u75c5\u9662\u7b49\u4e2d\u7684\uff09\u88ab\u6536\u5bb9\u8005", "mean_en": "a person who is kept in a prison or mental hospital", "sentence": "This inmate is being taken to his cell.", "sentence_trans": "\u8fd9\u4e2a\u56da\u72af\u6b63\u88ab\u5e26\u53bb\u4ed6\u7684\u7262\u623f\u3002", "sentence_phrase": "", "word_etyma": "", "cloze_data": {"syllable": "in-mate", "cloze": "[in]-mate", "options": ["en|on|un|an|e|i|a|o|u"], "tips": [["[in]", "[in]by"]]}}