{"word": "intricate", "accent": "/\u02c8\u026antr\u026ak\u0259t/", "mean_cn": "adj.\u9519\u7efc\u590d\u6742\u7684", "mean_en": "having a lot of different parts and small details that fit together", "sentence": "The inside of this watch is quite intricate.", "sentence_trans": "\u8fd9\u53ea\u624b\u8868\u7684\u5185\u90e8\u6784\u9020\u5341\u5206\u590d\u6742\u7cbe\u7ec6\u3002", "sentence_phrase": "", "word_etyma": "", "cloze_data": {"syllable": "in-tri-cate", "cloze": "[in]-tri-cate", "options": ["en|on|un|an|e|i|a|o|u"], "tips": [["[in]", "[in]by"]]}}