{"word": "journalism", "accent": "/\u02c8d\u0292\u025c\u02d0rn\u0259l\u026az\u0259m/", "mean_cn": "n.\u65b0\u95fb\u4e1a", "mean_en": "the work of collecting and writing news stories for newspapers, magazines, radio, television or online news sites; the news stories that are written", "sentence": "They work in journalism and broadcast news as anchors.", "sentence_trans": "\u4ed6\u4eec\u4ece\u4e8b\u65b0\u95fb\u884c\u4e1a\uff0c\u4f5c\u4e3a\u4e3b\u64ad\u64ad\u62a5\u65b0\u95fb\u3002", "sentence_phrase": "", "word_etyma": "journal\u65e5\u62a5 \uff0b ism\u540d\u8bcd\u540e\u7f00 \u2192 journalism\u65b0\u95fb\u4e1a", "cloze_data": {"syllable": "jour-nal-ism", "cloze": "j[our]-nal-ism", "options": ["oar|oor|oul|uir"], "tips": [["adj[our]nal", "j[our]nal"]]}}