{"word": "kick", "accent": "/k\u026ak/", "mean_cn": "v.\u8e22\uff1b\u8e22\u817f\uff1b  n.\u8e22", "mean_en": "to hit somebody/something with your foot; (in sports such as football (soccer ) and rugby) to score points by kicking the ball", "sentence": "The soccer player kicked the ball into the net. Goal!", "sentence_trans": "\u8fd9\u4e2a\u8db3\u7403\u8fd0\u52a8\u5458\u8e22\u8fdb\u4e86\u7403\uff0c\u5f97\u5206\uff01", "sentence_phrase": "", "word_etyma": "", "cloze_data": {"syllable": "kick", "cloze": "ki[ck]", "options": ["que|kn|ng|nk"], "tips": [["beki[ck]", "ki[ck]er"]]}}