{"word": "league", "accent": "/li\u02d0\u0261/", "mean_cn": "n. \u793e\u56e2\uff1b\u8054\u76df\uff1b  v. \u4f7f\u2026\u2026\u7ed3\u76df\uff0c\u4e0e\u2026\u2026\u8054\u5408", "mean_en": "a group of sports teams who all play each other to earn points and find which team is best", "sentence": "You are so good! You should join our soccer league!", "sentence_trans": "\u4f60\u5f88\u5389\u5bb3\uff01\u4f60\u5e94\u8be5\u52a0\u5165\u6211\u4eec\u7684\u8db3\u7403\u793e\u56e2\uff01", "sentence_phrase": "", "word_etyma": "", "cloze_data": {"syllable": "league", "cloze": "lea[gue]", "options": ["dge|geo|dj|ge"], "tips": [["enlea[gue]", "inlea[gue]"]]}}