{"word": "microprocessor", "accent": "/\u02ccma\u026akro\u028a\u02c8pro\u028ases\u0259r/", "mean_cn": "n. \u5fae\u5904\u7406\u5668", "mean_en": "a small unit of a computer that contains all the functions of the central processing unit", "sentence": "The microprocessor in my old computer is too slow.", "sentence_trans": "\u6211\u65e7\u7535\u8111\u7684\u5904\u7406\u5668\u592a\u6162\u4e86\u3002", "sentence_phrase": "", "word_etyma": "micro\u5fae + process\u5411\u524d\u884c\u8fdb\u7684\u8fc7\u7a0b=\u5904\u7406 + or\u8868\u7269 \u2192 microprocessor\u5fae\u5904\u7406\u5668", "cloze_data": {}}