{"word": "mighty", "accent": "/\u02c8ma\u026ati/", "mean_cn": "adj.\u5f3a\u5927\u7684\uff0c\u5f3a\u6709\u529b\u7684\uff1b  adv.\u975e\u5e38", "mean_en": "very strong and powerful; large and impressive", "sentence": "Lions are the most mighty of all animals in Africa.", "sentence_trans": "\u72ee\u5b50\u662f\u975e\u6d32\u5927\u9646\u4e0a\u6700\u5f3a\u5927\u7684\u52a8\u7269\u3002", "sentence_phrase": "", "word_etyma": "might\u529b\u91cf +  y\u5f62\u5bb9\u8bcd\u540e\u7f00 \u2192 mighty\u5f3a\u6709\u529b\u7684", "cloze_data": {"syllable": "mighty", "cloze": "m[igh]ty", "options": ["ough|eigh|ign|ind"], "tips": [["unm[igh]ty", "m[igh]tyship"]]}}