{"word": "mold", "accent": "/mo\u028ald/", "mean_cn": "vt. \u5851\u9020\uff1b\u4f7f\u5f62\u6210\uff1b  n. \u9709\u83cc\uff1b\u6a21\u5b50\uff1b\u6c14\u8d28", "mean_en": "to shape a soft substance into a particular form or object by pressing it or by putting it into a mold", "sentence": "I mold the clay with my hands to make a cup.", "sentence_trans": "\u6211\u7528\u624b\u628a\u9ecf\u571f\u5851\u9020\u6210\u4e00\u4e2a\u676f\u5b50\u3002", "sentence_phrase": "mold the clay", "word_etyma": "", "cloze_data": {"syllable": "mold", "cloze": "m[old]", "options": ["olt|olk|oll|ost"], "tips": [["m[old]er", "rem[old]"]]}}