{"word": "monkey", "accent": "/\u02c8m\u028c\u014bki/", "mean_cn": "n.\u7334\u5b50", "mean_en": "an animal with a long tail, that climbs trees and lives in hot countries. There are several types of monkey and they are related to apes and humans.", "sentence": "Monkeys are very clever animals.", "sentence_trans": "\u7334\u5b50\u662f\u5341\u5206\u806a\u660e\u7684\u52a8\u7269\u3002", "sentence_phrase": "", "word_etyma": "", "cloze_data": {"syllable": "mon-key", "cloze": "mon-k[ey]", "options": ["aa|ai|ei|ay|aw|a"], "tips": [["unk[ey]", "donk[ey]"]]}}