{"word": "odyssey", "accent": "/\u02c8\u0251\u02d0d\u0259si/", "mean_cn": "n. \u5965\u5fb7\u8d5b", "mean_en": "a Greek epic poem (attributed to Homer) describing the journey of Odysseus after the fall of Troy", "sentence": "An odyssey is a long exciting journey where lots of things can happen.", "sentence_trans": "\u5965\u5fb7\u8d5b\u662f\u6307\u4e00\u6bb5\u6f2b\u957f\u800c\u6fc0\u52a8\u4eba\u5fc3\u7684\u65c5\u7a0b\uff0c\u671f\u95f4\u53ef\u4ee5\u53d1\u751f\u5f88\u591a\u4e8b\u60c5\u3002", "sentence_phrase": "", "word_etyma": "", "cloze_data": {"syllable": "Odyssey", "cloze": "Odyss[ey]", "options": ["aa|ai|ei|ay|aw|a"], "tips": [[]]}}