{"word": "outing", "accent": "/\u02c8a\u028at\u026a\u014b/", "mean_cn": "n.\u77ed\u9014\u65c5\u6e38", "mean_en": "a brief trip that people take for fun usually as a group", "sentence": "The kids on the school trip are enjoying their spring outing.", "sentence_trans": "\u53c2\u52a0\u5b66\u6821\u90ca\u6e38\u7684\u5b69\u5b50\u4eec\u6b63\u5728\u4eab\u53d7\u4ed6\u4eec\u7684\u6625\u6e38\u3002", "sentence_phrase": "spring outing", "word_etyma": "out\u51fa + ing\u540d\u8bcd\u540e\u7f00 \u2192 outing \u8fdc\u8db3\uff0c\u51fa\u6e38", "cloze_data": {"syllable": "out-ing", "cloze": "out-[ing]", "options": ["ion|ang|ong|ung"], "tips": [["[ing]", "ap[ing]"]]}}