{"word": "perplex", "accent": "/p\u0259r\u02c8pleks/", "mean_cn": "v. \u4f7f\u56f0\u60d1", "mean_en": "if something perplexes you, it makes you confused or worried because you do not understand it", "sentence": "The problem perplexes the woman; she is very confused.", "sentence_trans": "\u8fd9\u4e2a\u95ee\u9898\u5f88\u8d39\u89e3\uff0c\u5979\u597d\u56f0\u60d1\u3002", "sentence_phrase": "", "word_etyma": "per\u8d2f\u7a7f\uff0c\u81ea\u59cb\u81ea\u7ec8 + plex\u91cd\u53e0 \u2192 \u59cb\u7ec8\u91cd\u53e0 \u2192 \u8ff7\u60d1", "cloze_data": {"syllable": "per-plex", "cloze": "per-[ple]x", "options": ["tle|dle|ble|cle|gle|kle"], "tips": [["du[ple]x", "[ple]x"]]}}