{"word": "physician", "accent": "/f\u026a\u02c8z\u026a\u0283n/", "mean_cn": "n. \u5185\u79d1\u533b\u751f", "mean_en": "a doctor, especially one who is a specialist in general medicine and not surgery", "sentence": "My physician told me to eat more fruits and vegetables.", "sentence_trans": "\u6211\u7684\u5185\u79d1\u533b\u751f\u544a\u8bc9\u6211\u8981\u591a\u5403\u6c34\u679c\u548c\u852c\u83dc\u3002", "sentence_phrase": "", "word_etyma": "phys\u751f\u7406\u9886\u57df + ician\u8868\u4e13\u5bb6\uff0c\u4ece\u4e8b\u67d0\u804c\u4e1a\u7684\u4eba \u2192 physician\u5185\u79d1\u533b\u751f", "cloze_data": {"syllable": "physi-cian", "cloze": "physi-c[ia]n", "options": ["eo|io|ew|yr|i|a"], "tips": [["asc[ia]n", "Dac[ia]n"]]}}