{"word": "pick up", "accent": "/p\u026ak \u028cp/", "mean_cn": "phr.\u6361\u8d77\uff0c\u62ff\u8d77\uff1b\u642d\u8f7d\uff0c\u62ff\u56de\uff1b\u83b7\u5f97\uff0c\u5b66\u4f1a", "mean_en": "to go somewhere in your car and collect somebody who is waiting for you", "sentence": "Many volunteers are helping in the park to pick up trash.", "sentence_trans": "\u8bb8\u591a\u5fd7\u613f\u8005\u6b63\u5e2e\u5fd9\u5728\u516c\u56ed\u91cc\u6361\u5783\u573e\u3002", "sentence_phrase": "", "word_etyma": "", "cloze_data": {}}