{"word": "porous", "accent": "/\u02c8p\u0254\u02d0r\u0259s/", "mean_cn": "adj. \u53ef\u6e17\u900f\u7684\uff0c\u591a\u5b54\u7684\uff0c\u53ef\u7a7f\u8d8a\u7684", "mean_en": "having many small holes that allow water or air to pass through slowly", "sentence": "Sponges are porous meaning they can absorb water.", "sentence_trans": "\u6d77\u7ef5\u662f\u591a\u5b54\u7684\uff0c\u8fd9\u610f\u5473\u7740\u5b83\u4eec\u53ef\u4ee5\u5438\u6c34\u3002", "sentence_phrase": "", "word_etyma": "por\u6c14\u5b54 + ous\u2026\u2026\u7684 \u2192 porous\u591a\u5b54\u6e17\u6c34\u7684\uff1b\u80fd\u6e17\u900f\u7684\uff1b\u6709\u6c14\u5b54\u7684", "cloze_data": {"syllable": "porous", "cloze": "p[or]ous", "options": ["ar|er|ir|ur|a"], "tips": [["bip[or]ous", "imp[or]ous"]]}}