{"word": "prediction", "accent": "/pr\u026a\u02c8d\u026ak\u0283n/", "mean_cn": "n.\u9884\u6d4b\uff0c\u9884\u8a00", "mean_en": "a statement that says what you think will happen; the act of making such a statement", "sentence": "The manager showed his predictions for the year to his team.", "sentence_trans": "\u7ecf\u7406\u5411\u4ed6\u7684\u56e2\u961f\u5c55\u793a\u4e86\u4ed6\u5bf9\u4eca\u5e74\u60c5\u51b5\u7684\u9884\u6d4b\u3002", "sentence_phrase": "", "word_etyma": "pre\u9884\u5148 + dict\u8bf4\u9884\u8a00 + ion\u540d\u8bcd \u2192 prediction\u9884\u544a", "cloze_data": {"syllable": "pre-dic-tion", "cloze": "pre-dic-t[ion]", "options": ["ing|ang|ong|ung"], "tips": [["act[ion]", "dat[ion]"]]}}