{"word": "preposition", "accent": "/\u02ccprep\u0259\u02c8z\u026a\u0283n/", "mean_cn": "n. \u524d\u7f6e\u8bcd\uff0c\u4ecb\u8bcd", "mean_en": "a word or group of words, such as in, from, to, out of and on behalf of, used before a noun or pronoun to show place, position, time or method", "sentence": "Prepositions are usually used before nouns to give additional information.", "sentence_trans": "\u4ecb\u8bcd\u901a\u5e38\u7528\u5728\u540d\u8bcd\u524d\u6765\u7ed9\u51fa\u989d\u5916\u7684\u4fe1\u606f\u3002", "sentence_phrase": "", "word_etyma": "pre\u2026\u524d\u7684\uff0c\u9884\u5148 + position\u4f4d\u7f6e \u2192 \u4f4d\u7f6e\u653e\u5728\u524d\u9762 \u2192 \u524d\u7f6e\u8bcd\uff0c\u4ecb\u8bcd", "cloze_data": {"syllable": "prepo-si-tion", "cloze": "prepo-si-t[ion]", "options": ["ing|ang|ong|ung"], "tips": [["act[ion]", "dat[ion]"]]}}