{"word": "prick", "accent": "/pr\u026ak/", "mean_cn": "n. \u624e\uff0c\u4e00\u523a\uff0c\u523a\u75db\uff0c\u9525\uff0c\u9634\u830e\uff1b  v. \u523a\uff0c\u6233\uff0c\u523a\u75db\uff0c\u7ad6\u8d77", "mean_en": "a penis; an offensive word for a stupid or unpleasant man; an act of making a very small hole in something with a sharp point; a slight pain caused by a sharp point or something that feels like a sharp point", "sentence": "A prick from one of these thorns will draw blood.", "sentence_trans": "\u5728\u8fd9\u4e0a\u9762\u968f\u4fbf\u4e00\u523a\u90fd\u4f1a\u624e\u51fa\u8840\u3002", "sentence_phrase": "", "word_etyma": "", "cloze_data": {"syllable": "prick", "cloze": "pri[ck]", "options": ["que|kn|ng|nk"], "tips": [["pri[ck]er", "pri[ck]et"]]}}