{"word": "product", "accent": "/\u02c8pr\u0251\u02d0d\u028ckt/", "mean_cn": "n.\u4ea7\u54c1\uff1b\uff08\u4e58\uff09\u79ef", "mean_en": "a cream, jelly or liquid that you put on your hair or skin to make it look better; a thing that is grown or produced, usually for sale; a thing produced during a natural, chemical or industrial process", "sentence": "We sell a range of products for skincare and health.", "sentence_trans": "\u6211\u4eec\u5356\u4e00\u7cfb\u5217\u62a4\u80a4\u548c\u4fdd\u5065\u4ea7\u54c1\u3002", "sentence_phrase": "", "word_etyma": "pro\u5411\u524d + duct\u5f15\u5bfc\uff0c\u5e26\u6765 \u2192 \u5f15\u51fa\u7684\u4e1c\u897f \u2192 product\u4ea7\u7269\uff0c\u4ea7\u54c1", "cloze_data": {"syllable": "prod-uct", "cloze": "prod-[u]ct", "options": ["a|e|i|o|aa|ae|ai|ao|au|ea|ee|ei|eo|eu|ia|ie|ii|io|iu|oa|oe|oi|oo|ou|ua|ue|ui|uo|uu|ay|ey|ow|oy|ur|al|ir|or|er|ar"], "tips": [["pl[u]g", "pl[u]s"]]}}