{"word": "radiation", "accent": "/\u02ccre\u026adi\u02c8e\u026a\u0283n/", "mean_cn": "n.\u8f90\u5c04\u7269\uff1b\u653e\u5c04\u7269", "mean_en": "a type of dangerous and powerful energy that is produced by radioactive substances and nuclear reactions", "sentence": "Don't get closer to radiation if you are not in a protective suit.", "sentence_trans": "\u6ca1\u6709\u7a7f\u9632\u8f90\u5c04\u670d\u5c31\u4e0d\u8981\u9760\u8fd1\u8f90\u5c04\u7269\u3002", "sentence_phrase": "get closer to radiation", "word_etyma": "radi\u8f90\u5c04 + ation\u8868\u793a\u884c\u4e3a\u3001\u72b6\u6001\u3001\u8fc7\u7a0b\u3001\u7ed3\u679c \u2192 radiation\u8f90\u5c04\u80fd", "cloze_data": {"syllable": "ra-di-a-tion", "cloze": "ra-di-[a]-t[ion]", "options": ["e|i|o|u", "ing|ang|ong|ung"], "tips": [["[a]", "[a]ba"], ["act[ion]", "dat[ion]"]]}}