{"word": "regulation", "accent": "/\u02ccre\u0261ju\u02c8le\u026a\u0283n/", "mean_cn": "n.\u89c4\u7ae0\uff0c\u6cd5\u89c4\uff0c\u6761\u4f8b", "mean_en": "an official rule made by a government or some other authority", "sentence": "The traffic police is introducing traffic rules and regulations to us.", "sentence_trans": "\u4ea4\u8b66\u5728\u5411\u6211\u4eec\u4ecb\u7ecd\u4ea4\u901a\u6cd5\u89c4\u3002", "sentence_phrase": "traffic rules and regulations", "word_etyma": "regul\u89c4\u5219\u3001\u7edf\u6cbb + ation\u8868\u540d\u8bcd \u2192 \u6709\u89c4\u5219\u7684 \u2192 regulation\u89c4\u5219\uff0c\u89c4\u7ae0", "cloze_data": {"syllable": "re-gu-la-tion", "cloze": "re-gu-l[a]-t[ion]", "options": ["e|i|o|u", "ing|ang|ong|ung"], "tips": [["Il[a]", "l[a]"], ["act[ion]", "dat[ion]"]]}}