{"word": "scarcity", "accent": "/\u02c8skers\u0259ti/", "mean_cn": "n. \u7f3a\u4e4f\uff0c\u4e0d\u8db3", "mean_en": "if there is a scarcity of something, there is not enough of it and it is difficult to obtain it", "sentence": "Water scarcity is a big problem facing many people around the world.", "sentence_trans": "\u6c34\u8d44\u6e90\u77ed\u7f3a\u662f\u4e16\u754c\u4e0a\u5f88\u591a\u4eba\u90fd\u9762\u4e34\u7684\u4e00\u4e2a\u91cd\u5927\u95ee\u9898\u3002", "sentence_phrase": "", "word_etyma": "scarc\u7f3a\u4e4f\u7684 + ity \u6784\u6210\u62bd\u8c61\u540d\u8bcd\uff0c\u8868\u793a\u6027\u8d28\u3001\u72b6\u6001 \u2192 scarcity\u7f3a\u4e4f\uff0c\u4e0d\u8db3", "cloze_data": {"syllable": "scarci-ty", "cloze": "sc[ar]ci-ty", "options": ["er|ir|or|ur|a"], "tips": [[]]}}