{"word": "security", "accent": "/s\u026a\u02c8kj\u028ar\u0259ti/", "mean_cn": "n.\u5b89\u5168\uff1b\u9632\u62a4\u63aa\u65bd", "mean_en": "a place at an airport where you go after your passport has been checked so that officials can find out if you are carrying illegal drugs or weapons", "sentence": "You must go through the security check at the airport.", "sentence_trans": "\u5728\u673a\u573a\uff0c\u4f60\u5fc5\u987b\u8fdb\u884c\u5b89\u5168\u68c0\u67e5\u3002", "sentence_phrase": "security check", "word_etyma": "secur\u5b89\u5168\u7684 + ity\u540d\u8bcd\u540e\u7f00 \u2192 security\u5b89\u5168\uff1b\u8bc1\u5238", "cloze_data": {"syllable": "se-cu-ri-ty", "cloze": "se-c[u]-r[i]-ty", "options": ["a|e|i|o|aa|ae|ai|ao|au|ea|ee|ei|eo|eu|ia|ie|ii|io|iu|oa|oe|oi|oo|ou|ua|ue|ui|uo|uu|ay|ey|ow|oy|ur|al|ir|or|er|ar", "a|e|o|u|aa|ae|ai|ao|au|ea|ee|ei|eo|eu|ia|ie|ii|io|iu|oa|oe|oi|oo|ou|ua|ue|ui|uo|uu|ay|ey|ow|oy|ur|al|ir|or|er|ar"], "tips": [["do-c[u]-ment", "e-va-l[u]-ate"], ["mi-n[i]-mum", "mul-t[i]-ply"]]}}