{"word": "self", "accent": "/self/", "mean_cn": "n.\u81ea\u5df1\uff0c\u81ea\u6211\uff0c\u81ea\u8eab", "mean_en": "the type of person you are, especially the way you normally behave, look or feel; a person\u2019s personality or character that makes them different from other people; used to refer to a person", "sentence": "She's looking like her confident old self again.", "sentence_trans": "\u5979\u770b\u8d77\u6765\u53c8\u50cf\u4ece\u524d\u90a3\u4e2a\u81ea\u4fe1\u7684\u81ea\u5df1\u4e86\u3002", "sentence_phrase": "", "word_etyma": "", "cloze_data": {"syllable": "self", "cloze": "s[el]f", "options": ["al|le|nl|ol"], "tips": [["res[el]f", "its[el]f"]]}}