{"word": "sheep", "accent": "/\u0283i\u02d0p/", "mean_cn": "n.\u7ef5\u7f8a\uff08\u5355\u590d\u6570\u540c\u5f62\uff09\uff1b\u80c6\u5c0f\u9b3c", "mean_en": "an animal with a thick coat, kept on farms for its meat (called mutton or lamb ) or its wool", "sentence": "Sheep are raised to produce wool.", "sentence_trans": "\u4eba\u4eec\u517b\u7f8a\u662f\u4e3a\u4e86\u4ea7\u7f8a\u6bdb\u3002", "sentence_phrase": "", "word_etyma": "", "cloze_data": {"syllable": "sheep", "cloze": "[sh]eep", "options": ["tch|chr|sch|th"], "tips": [["[sh]eepish", "[sh]eepman"]]}}