{"word": "skillful", "accent": "/\u02c8sk\u026alfl/", "mean_cn": "adj.\u5a34\u719f\u7684", "mean_en": "having the training, knowledge, and experience that is needed to do something well; having a lot of skill", "sentence": "They're very skillful skateboarders!", "sentence_trans": "\u4ed6\u4eec\u662f\u6280\u672f\u6781\u5176\u5a34\u719f\u7684\u6ed1\u677f\u8fd0\u52a8\u5458\uff01", "sentence_phrase": "", "word_etyma": "skill\u6280\u672f + ful\u2026\u7684 \u2192 \u6709\u6280\u672f\u7684 \u2192 skillful\u719f\u7ec3\u7684", "cloze_data": {"syllable": "skill-ful", "cloze": "sk[i]ll-ful", "options": ["a|e|o|u"], "tips": [["outsk[i]ll", "sk[i]ll"]]}}