{"word": "soft drink", "accent": "/\u02ccs\u0254\u02d0ft \u02c8dr\u026a\u014bk/", "mean_cn": "phr. \uff08\u4e0d\u542b\u9152\u7cbe\u7684\uff09\u6e05\u51c9\u996e\u6599", "mean_en": "a cold drink that is usually sweet, does not contain alcohol, and is often sold in bottles or cans", "sentence": "Thanks, I don't want a beer\u2014I'd rather have a soft drink.", "sentence_trans": "\u8c22\u8c22\uff0c\u6211\u4e0d\u8981\u5564\u9152\uff0c\u6211\u5b81\u613f\u559d\u8f6f\u996e\u6599\u3002", "sentence_phrase": "have a soft drink", "word_etyma": "", "cloze_data": {}}