{"word": "stand by sth.", "accent": "/st\u00e6nd ba\u026a \u02c8s\u028cm\u03b8\u026a\u014b/", "mean_cn": "phr. \u4fe1\u5b88", "mean_en": "support materially or financially", "sentence": "He stood by his decision to feed the needy, despite his family's disagreement.", "sentence_trans": "\u5c3d\u7ba1\u5bb6\u4eba\u4e0d\u540c\u610f\uff0c\u4ed6\u4f9d\u7136\u4fe1\u5b88\u81ea\u5df1\u7684\u51b3\u5b9a\uff0c\u63a5\u6d4e\u9700\u8981\u5e2e\u52a9\u7684\u4eba\u3002", "sentence_phrase": "", "word_etyma": "", "cloze_data": {}}