{"word": "streak", "accent": "/stri\u02d0k/", "mean_cn": "n. \u6761\u7eb9\uff0c\u6761\u75d5\uff0c\u8272\u7ebf\uff1b  v. \u6210\u6761\u7eb9", "mean_en": "a long thin mark or line that is a different colour from the surface it is on; a part of a person\u2019s character, especially an unpleasant part; a series of successes or failures, especially in a sport or in gambling", "sentence": "She drew several black streaks on the paper using the writing brush.", "sentence_trans": "\u5979\u7528\u6bdb\u7b14\u5728\u7eb8\u4e0a\u753b\u4e86\u51e0\u6761\u9ed1\u8272\u6761\u7eb9\u3002", "sentence_phrase": "", "word_etyma": "", "cloze_data": {"syllable": "streak", "cloze": "str[ea]k", "options": ["ee|ie|ii|ye|e"], "tips": [["bestr[ea]k", "str[ea]ker"]]}}