{"word": "sunshine", "accent": "/\u02c8s\u028cn\u0283a\u026an/", "mean_cn": "n.\u65e5\u5149\uff0c\u65e5\u7167", "mean_en": "the sun's light or rays; warmth and light from the sun", "sentence": "The sunshine broke through the clouds.", "sentence_trans": "\u9633\u5149\u7a7f\u900f\u4e86\u4e91\u5c42\u3002", "sentence_phrase": "", "word_etyma": "sun\u592a\u9633 + shine\u5149\u4eae \u2192 sunshine\u65e5\u5149\uff0c\u65e5\u7167", "cloze_data": {"syllable": "sun-shine", "cloze": "sun-[sh]ine", "options": ["tch|chr|sch|th"], "tips": [["[sh]ine", "ar[sh]ine"]]}}