{"word": "terribly", "accent": "/\u02c8ter\u0259bli/", "mean_cn": "adv.\u6781\u5ea6\u5730\uff0c\u975e\u5e38\uff1b\u53ef\u6015\u5730", "mean_en": "very", "sentence": "He was terribly sorry for what he had done.", "sentence_trans": "\u4ed6\u5bf9\u4ed6\u505a\u8fc7\u7684\u4e8b\u611f\u5230\u975e\u5e38\u62b1\u6b49\u3002", "sentence_phrase": "", "word_etyma": "terr=frighten\u6050\uff0c\u6015 + ibly\u2026\u2026\u5730 \u2192 terribly\u975e\u5e38\uff1b\u53ef\u6015\u5730\uff1b\u6781\u5ea6\u5730", "cloze_data": {"syllable": "ter-ri-bly", "cloze": "t[er]ri-bly", "options": ["ar|ir|or|ur|a"], "tips": [["t[er]rify", "t[er]rier"]]}}