{"word": "unsuitable", "accent": "/\u028cn\u02c8su\u02d0t\u0259bl/", "mean_cn": "adj. \u4e0d\u9002\u5408\u7684", "mean_en": "not right or appropriate for a particular person, purpose or occasion", "sentence": "This tool is unsuitable for the job.", "sentence_trans": "\u8fd9\u4e2a\u5de5\u5177\u4e0d\u9002\u5408\u8fd9\u4e2a\u5de5\u4f5c\u3002", "sentence_phrase": "", "word_etyma": "un\u4e0d + suit\u9002\u5408 + able\u80fd\u2026\u2026\u7684 \u2192 unsuitable\u4e0d\u9002\u5408\u7684\uff1b\u4e0d\u76f8\u79f0\u7684", "cloze_data": {"syllable": "un-suit-able", "cloze": "un-suit-a[ble]", "options": ["tle|dle|ple|cle|gle|kle"], "tips": [["ena[ble]", "lia[ble]"]]}}