{"word": "vanity", "accent": "/\u02c8v\u00e6n\u0259ti/", "mean_cn": "n. \u81ea\u8d1f\uff1b\uff08\u5e26\u955c\u5b50\u7684\uff09\u68b3\u5986\u53f0", "mean_en": "too much pride in your own appearance, abilities or achievements", "sentence": "It's clear that this man's level of vanity is far too high!", "sentence_trans": "\u8fd9\u4e2a\u7537\u4eba\u592a\u81ea\u8d1f\u4e86\uff01", "sentence_phrase": "", "word_etyma": "van\u7a7a + ity\u8868\u540d\u8bcd \u2192 vanity\u7a7a\u865a", "cloze_data": {"syllable": "va-ni-ty", "cloze": "va-n[i]-ty", "options": ["a|e|o|u"], "tips": [["Bin[i]", "n[i]"]]}}