{"word": "vowel", "accent": "/\u02c8va\u028a\u0259l/", "mean_cn": "n.\u5143\u97f3\u5b57\u6bcd\uff1b\u5143\u97f3", "mean_en": "a letter that represents a vowel sound. In English the vowels are a, e, i, o and u.", "sentence": "English has five vowels - a, e, i, o, and u.", "sentence_trans": "\u82f1\u8bed\u4e2d\u6709\u4e94\u4e2a\u5143\u97f3\u5b57\u6bcd\uff0c\u5b83\u4eec\u662fa\u3001e\u3001i\u3001o\u3001u\u3002", "sentence_phrase": "", "word_etyma": "", "cloze_data": {"syllable": "vow-el", "cloze": "vow-[el]", "options": ["al|le|nl|ol"], "tips": [["Ax[el]", "du[el]"]]}}