{"word": "wary", "accent": "/\u02c8weri/", "mean_cn": "adj. \u8c28\u614e\u7684\uff0c\u5c0f\u5fc3\u7684\uff0c\u63d0\u9632\u7684", "mean_en": "careful when dealing with somebody/something because you think that there may be a danger or problem", "sentence": "The cat has a wary stare at someone coming close.", "sentence_trans": "\u732b\u54aa\u8c28\u614e\u5730\u76ef\u7740\u6b63\u5728\u9760\u8fd1\u5b83\u7684\u4eba\u3002", "sentence_phrase": "a wary stare", "word_etyma": "war\u6ce8\u89c6\uff0c\u770b\u62a4 + y\u5f62\u5bb9\u8bcd\u540e\u7f00 \u2192 \u8b66\u60d5\u7684\uff0c\u8c28\u614e\u7684", "cloze_data": {"syllable": "wary", "cloze": "w[ar]y", "options": ["er|ir|or|ur|a"], "tips": [["unw[ar]y"]]}}