{"word": "yoke", "accent": "/jo\u028ak/", "mean_cn": "n. \u725b\u8f6d\uff1b\u67b7\u9501\uff1b\u7ebd\u5e26\uff1b  v. \u7ed3\u5408\uff1b\u8fde\u7ed3", "mean_en": "a long piece of wood that is fastened across the necks of two animals, especially oxen, so that they can pull heavy loads", "sentence": "The two oxen are attached together by a yoke over their necks.", "sentence_trans": "\u8116\u5b50\u4e0a\u7684\u725b\u8f6d\u5c06\u8fd9\u4e24\u5934\u725b\u62f4\u5728\u4e86\u4e00\u8d77\u3002", "sentence_phrase": "a yoke over their necks", "word_etyma": "", "cloze_data": {"syllable": "yoke", "cloze": "yok[e]", "options": ["a|i|o|u"], "tips": [["upyok[e]", "unyok[e]"]]}}